tensorwatch_api/__init__.py
tensorwatch_api/twapi.py
tensorwatch_api-1.1.0.dist-info/licenses/LICENSE.txt
tensorwatch_api-1.1.0.dist-info/METADATA
tensorwatch_api-1.1.0.dist-info/WHEEL
tensorwatch_api-1.1.0.dist-info/top_level.txt
tensorwatch_api-1.1.0.dist-info/RECORD
