Metadata-Version: 2.4
Name: tensorwatch-api
Version: 1.1.0
Summary: Interactive Kafka stream visualization API for Jupyter using TensorWatch.
Home-page: https://github.com/costasrevi/jupyterstreamvis
Author: Konstantinos Revythis
Author-email: Konstantinos Revythis <krevythis@tuc.gr>
License: MIT
Project-URL: Homepage, https://github.com/costasrevi/jupyterstreamvis
Project-URL: Source, https://github.com/costasrevi/jupyterstreamvis
Keywords: kafka,tensorwatch,jupyter,streaming,visualization
Classifier: Programming Language :: Python :: 3
Classifier: License :: OSI Approved :: MIT License
Classifier: Operating System :: OS Independent
Classifier: Development Status :: 4 - Beta
Classifier: Intended Audience :: Developers
Classifier: Topic :: Software Development :: Libraries :: Python Modules
Requires-Python: >=3.9
License-File: LICENSE.txt
Requires-Dist: tensorwatch
Requires-Dist: ipywidgets
Requires-Dist: matplotlib
Requires-Dist: confluent-kafka; extra == "kafka"
Requires-Dist: pykafka; extra == "pykafka"
Dynamic: author
Dynamic: home-page
Dynamic: license-file
Dynamic: requires-python
